convis/optimizer.py
convis/misc_utils.py
convis/samples.py
convis/tests.py
convis/misc_splines.py
convis/kernels.py
convis/retina_virtualretina.py
convis/variable_describe.py
convis/streams.py
convis/__init__.py
convis/models.py
convis/utils.py
convis/retina.py
convis/io.py
convis/wx_streams.py
convis/layers.py
convis/derivalbe_kernels.py
convis/variables.py
convis/base.py
convis/__main__.py
convis/o.py
convis/analysis.py
convis/png.py
convis/numerical_filters.py
convis/theano_utils.py
convis/filters/spiking.py
convis/filters/simple.py
convis/filters/__init__.py
convis/filters/retina.py
convis/filters/retina_old.py
convis-0.6.3.dist-info/WHEEL
convis-0.6.3.dist-info/top_level.txt
convis-0.6.3.dist-info/metadata.json
convis-0.6.3.dist-info/RECORD
convis-0.6.3.dist-info/DESCRIPTION.rst
convis-0.6.3.dist-info/METADATA
