Metadata-Version: 2.0
Name: convis
Version: 0.6.3
Summary: Convolutional Vision Model
Home-page: https://github.com/jahuth/convis
Author: Jacob Huth
Author-email: jahuth@uos.de
License: UNKNOWN
Download-URL: https://github.com/jahuth/convis/tarball/0.6.3
Keywords: vision model,retina model
Platform: UNKNOWN
Requires-Dist: matplotlib
Requires-Dist: litus
Requires-Dist: numpy
Requires-Dist: future
